mop-uutils/__init__.py
mop-uutils/base_model_wrapper.py
mop-uutils/constant.py
mop-uutils/inference_wrapper.py
mop-uutils/util.py
mop-uutils-now/__init__.py
mop-uutils-now/base_model_wrapper.py
mop-uutils-now/constant.py
mop-uutils-now/inference_wrapper.py
mop-uutils-now/util.py
src/__init__.py
src/base_model_wrapper.py
src/constant.py
src/inference_wrapper.py
src/util.py
src/mop-uutils/__init__.py
src/mop-uutils/base_model_wrapper.py
src/mop-uutils/constant.py
src/mop-uutils/inference_wrapper.py
src/mop-uutils/util.py
test-mop-utils/__init__.py
test-mop-utils/base_model_wrapper.py
test-mop-utils/constant.py
test-mop-utils/inference_wrapper.py
test-mop-utils/util.py
test_utils_mop/__init__.py
test_utils_mop/base_model_wrapper.py
test_utils_mop/constant.py
test_utils_mop/inference_wrapper.py
test_utils_mop/util.py
test_utils_mop-2.3.dist-info/METADATA
test_utils_mop-2.3.dist-info/WHEEL
test_utils_mop-2.3.dist-info/top_level.txt
test_utils_mop-2.3.dist-info/RECORD
